kzr_snowflake/__init__.py
kzr_snowflake/cli.py
kzr_snowflake/kzr_snowflake.py
kzr_snowflake-0.1.1.dist-info/AUTHORS.rst
kzr_snowflake-0.1.1.dist-info/LICENSE
kzr_snowflake-0.1.1.dist-info/METADATA
kzr_snowflake-0.1.1.dist-info/WHEEL
kzr_snowflake-0.1.1.dist-info/entry_points.txt
kzr_snowflake-0.1.1.dist-info/top_level.txt
kzr_snowflake-0.1.1.dist-info/RECORD
